psmoe/__init__.py
psmoe/networks.py
psmoe/nyul.py
psmoe/nyul_landmarks.npy
psmoe/predictor.py
psmoe-0.1.4.5.dist-info/LICENSE
psmoe-0.1.4.5.dist-info/METADATA
psmoe-0.1.4.5.dist-info/WHEEL
psmoe-0.1.4.5.dist-info/top_level.txt
psmoe-0.1.4.5.dist-info/RECORD
