Metadata-Version: 2.1
Name: psmoe
Version: 0.1.4.5
Summary: A simple module for prostate segmentation of T2-W MRI sequences in Nifti format
Home-page: https://github.com/mpierangeli/prostate_segmentation_moe
Author: Martin Pierangeli
Author-email: marespierangeli@gmail.com
Project-URL: Source, https://github.com/mpierangeli/prostate_segmentation_moe
Keywords: UNet,ML,Prostate,Segmentations
Classifier: Intended Audience :: Developers
Classifier: License :: OSI Approved :: MIT License
Classifier: Programming Language :: Python :: 3.8
Classifier: Programming Language :: Python :: 3.9
Classifier: Programming Language :: Python :: 3.10
Classifier: Programming Language :: Python :: 3.11
License-File: LICENSE
Requires-Dist: numpy >=1.23.5
Requires-Dist: matplotlib >=3.6.2
Requires-Dist: opencv-python >=4.6.0.66
Requires-Dist: nibabel >=5.2.0
Requires-Dist: scipy >=1.9.3
Requires-Dist: gdown >=4.7.3
Requires-Dist: keras >=2.15.0
Requires-Dist: tensorflow >=2.15.0
